fpga/Xilinx/Cmod_A7/Max7219/debounce.sv
`timescale 1 ns / 1 ps

// Debounce module:
//
// ------------------------------------------------------------------------------------------
//
// The input data is debounced. The output data is high when the input data is high for
// DEBOUNCE_CYCLES clock cycles. The output data is low when the input data is low.
//
// ------------------------------------------------------------------------------------------

module debounce
    #(  parameter   DEBOUNCE_CYCLES = 4
    )(
        input       i_Clk,
        input       i_Data,
        output reg  o_Data
    );

    integer     r_Cycles = 0;
    reg         r_Data = 0;

    always @(posedge i_Clk) begin
        if (i_Data) begin
            if (r_Cycles == DEBOUNCE_CYCLES) begin
                r_Cycles <= 0;
                r_Data   <= 1;
            end
            else begin
                r_Cycles <= r_Cycles + 1;
            end
        end
        else begin
            r_Cycles <= 0;
            r_Data   <= 0;
        end
    end

    assign o_Data = r_Data;

endmodule

fpga/Xilinx/Cmod_A7/Max7219-fb/tb/debounce_tb.sv
`timescale 1 ns / 1 ps

module debounce_tb;

    localparam  DEBOUNCE_CYCLES = 4;

    reg         r_Rst;
    reg         r_Clk;
    reg         r_Data;
    reg         r_Debounced_Data;

    debounce
        #(  .DEBOUNCE_CYCLES (DEBOUNCE_CYCLES)
        ) debounce_0 (
            .i_Clk  (r_Clk),
            .i_Data (r_Data),
            .o_Data (r_Debounced_Data)
        );

    function void init();
        $dumpfile("debounce.vcd");
        $dumpvars(0);
        r_Rst = 1'b1;
        r_Clk = 1'b0;
        r_Data = 1'b0;
    endfunction

    initial begin
        init();
        #1 r_Rst = 1'b0;
        #2 r_Data <= ~r_Data;
        #3 r_Data <= ~r_Data;
        #7 r_Data <= ~r_Data;
        #3 r_Data <= ~r_Data;
        #30 r_Data <= ~r_Data;
        #50 r_Data <= ~r_Data;
        #200 $finish;
    end

    always begin
        #1 r_Clk = ~r_Clk;
    end

endmodule

fpga/Xilinx/Cmod_A7/Max7219-fb/build/PC101137/run/debounce.vcd
$date
	Sun Jan 11 23:21:06 2026
$end
$version
	Icarus Verilog
$end
$timescale
	1ps
$end
$scope module debounce_tb $end
$var wire 1 ! r_Debounced_Data $end
$var parameter 32 " DEBOUNCE_CYCLES $end
$var reg 1 # r_Clk $end
$var reg 1 $ r_Data $end
$var reg 1 % r_Rst $end
$scope function init $end
$upscope $end
$scope module debounce_0 $end
$var wire 1 # i_Clk $end
$var wire 1 $ i_Data $end
$var wire 1 ! o_Data $end
$var parameter 32 & DEBOUNCE_CYCLES $end
$var reg 1 ' r_Data $end
$var integer 32 ( r_Cycles [31:0] $end
$upscope $end
$upscope $end
$enddefinitions $end
$comment Show the parameter values. $end
$dumpall
b100 &
b100 "
$end
#0
$dumpvars
b0 (
0'
1%
0$
0#
0!
$end
#1000
1#
0%
#2000
0#
#3000
1$
1#
#4000
0#
#5000
b1 (
1#
#6000
0$
0#
#7000
b0 (
1#
#8000
0#
#9000
1#
#10000
0#
#11000
1#
#12000
0#
#13000
1$
1#
#14000
0#
#15000
b1 (
1#
#16000
0$
0#
#17000
b0 (
1#
#18000
0#
#19000
1#
#20000
0#
#21000
1#
#22000
0#
#23000
1#
#24000
0#
#25000
1#
#26000
0#
#27000
1#
#28000
0#
#29000
1#
#30000
0#
#31000
1#
#32000
0#
#33000
1#
#34000
0#
#35000
1#
#36000
0#
#37000
1#
#38000
0#
#39000
1#
#40000
0#
#41000
1#
#42000
0#
#43000
1#
#44000
0#
#45000
1#
#46000
1$
0#
#47000
b1 (
1#
#48000
0#
#49000
b10 (
1#
#50000
0#
#51000
b11 (
1#
#52000
0#
#53000
b100 (
1#
#54000
0#
#55000
1!
1'
b0 (
1#
#56000
0#
#57000
b1 (
1#
#58000
0#
#59000
b10 (
1#
#60000
0#
#61000
b11 (
1#
#62000
0#
#63000
b100 (
1#
#64000
0#
#65000
b0 (
1#
#66000
0#
#67000
b1 (
1#
#68000
0#
#69000
b10 (
1#
#70000
0#
#71000
b11 (
1#
#72000
0#
#73000
b100 (
1#
#74000
0#
#75000
b0 (
1#
#76000
0#
#77000
b1 (
1#
#78000
0#
#79000
b10 (
1#
#80000
0#
#81000
b11 (
1#
#82000
0#
#83000
b100 (
1#
#84000
0#
#85000
b0 (
1#
#86000
0#
#87000
b1 (
1#
#88000
0#
#89000
b10 (
1#
#90000
0#
#91000
b11 (
1#
#92000
0#
#93000
b100 (
1#
#94000
0#
#95000
b0 (
1#
#96000
0$
0#
#97000
0!
0'
1#
