fpga/Xilinx/Cmod_A7/Max7219-fb/design/lfsr.sv
`timescale 1 ns / 1 ps

// The implementation is based on an idea outlined in http://www.nandland.com
//
// A LFSR or Linear Feedback Shift Register is meant for generating pseudo-random
// data in FPGA. This module creates an LFSR whose width gets set by a parameter.
// The o_LFSR_Done will pulse for a duration of 1 clock period once all combinations
// of the LFSR are complete.  The number of clock
// cycles that it takes o_LFSR_Done to pulse is equal to 2^NUM_BITS-1. For
// example setting NUM_BITS to 5 means that o_LFSR_Done will pulse every
// 2^5-1 = 31 clock cycles. o_LFSR_Data will change on each clock cycle that
// the module is enabled.

module lfsr

    #(  parameter NUM_BITS = 4  // The number of bits in the LFSR
    )(
        input   i_Clk,
        input   i_Enable,   // Set on the positive edge of the clock to run LFSR
 
        // Optional Seed Value
        input                   i_Seed_DV,      // Set on the positive edge of the clock to load seed data
        input [NUM_BITS-1:0]    i_Seed_Data,    // Data to initialize the LFSR with
        
        output [NUM_BITS-1:0]   o_LFSR_Data,    // The current value of the LFSR (the initial value is 0)
        output                  o_LFSR_Done
    );
 
    reg [NUM_BITS:1] r_LFSR = '0;
    reg              r_XNOR = 1'b0;
 
 
    // Purpose: Load up LFSR with Seed if Data Valid (DV) pulse is detected.
    // Othewise just run LFSR when enabled.

    always @(posedge i_Clk) begin
        if (i_Enable == 1'b1) begin
            if (i_Seed_DV == 1'b1) begin
                r_LFSR <= i_Seed_Data;
            end else begin
                r_LFSR <= {r_LFSR[NUM_BITS-1:1], r_XNOR};
            end
        end
    end
 
    // Create Feedback Polynomials.  Based on Application Note:
    // http://www.xilinx.com/support/documentation/application_notes/xapp052.pdf

    always @(*) begin
        case (NUM_BITS)
        3: begin
            r_XNOR = r_LFSR[3] ^ ~r_LFSR[2];
        end
        4: begin
            r_XNOR = r_LFSR[4] ^ ~r_LFSR[3];
        end
        5: begin
            r_XNOR = r_LFSR[5] ^ ~r_LFSR[3];
        end
        6: begin
            r_XNOR = r_LFSR[6] ^ ~r_LFSR[5];
        end
        7: begin
            r_XNOR = r_LFSR[7] ^ ~r_LFSR[6];
        end
        8: begin
            r_XNOR = r_LFSR[8] ^ ~r_LFSR[6] ^ ~r_LFSR[5] ^ ~r_LFSR[4];
        end
        9: begin
            r_XNOR = r_LFSR[9] ^ ~r_LFSR[5];
        end
        10: begin
            r_XNOR = r_LFSR[10] ^ ~r_LFSR[7];
        end
        11: begin
            r_XNOR = r_LFSR[11] ^ ~r_LFSR[9];
        end
        12: begin
            r_XNOR = r_LFSR[12] ^ ~r_LFSR[6] ^ ~r_LFSR[4] ^ ~r_LFSR[1];
        end
        13: begin
            r_XNOR = r_LFSR[13] ^ ~r_LFSR[4] ^ ~r_LFSR[3] ^ ~r_LFSR[1];
        end
        14: begin
            r_XNOR = r_LFSR[14] ^ ~r_LFSR[5] ^ ~r_LFSR[3] ^ ~r_LFSR[1];
        end
        15: begin
            r_XNOR = r_LFSR[15] ^ ~r_LFSR[14];
        end
        16: begin
            r_XNOR = r_LFSR[16] ^ ~r_LFSR[15] ^ ~r_LFSR[13] ^ ~r_LFSR[4];
            end
        17: begin
            r_XNOR = r_LFSR[17] ^ ~r_LFSR[14];
        end
        18: begin
            r_XNOR = r_LFSR[18] ^ ~r_LFSR[11];
        end
        19: begin
            r_XNOR = r_LFSR[19] ^ ~r_LFSR[6] ^ ~r_LFSR[2] ^ ~r_LFSR[1];
        end
        20: begin
            r_XNOR = r_LFSR[20] ^ ~r_LFSR[17];
        end
        21: begin
            r_XNOR = r_LFSR[21] ^ ~r_LFSR[19];
        end
        22: begin
            r_XNOR = r_LFSR[22] ^ ~r_LFSR[21];
        end
        23: begin
            r_XNOR = r_LFSR[23] ^ ~r_LFSR[18];
        end
        24: begin
            r_XNOR = r_LFSR[24] ^ ~r_LFSR[23] ^ ~r_LFSR[22] ^ ~r_LFSR[17];
        end
        25: begin
            r_XNOR = r_LFSR[25] ^ ~r_LFSR[22];
        end
        26: begin
            r_XNOR = r_LFSR[26] ^ ~r_LFSR[6] ^ ~r_LFSR[2] ^ ~r_LFSR[1];
        end
        27: begin
            r_XNOR = r_LFSR[27] ^ ~r_LFSR[5] ^ ~r_LFSR[2] ^ ~r_LFSR[1];
        end
        28: begin
            r_XNOR = r_LFSR[28] ^ ~r_LFSR[25];
        end
        29: begin
            r_XNOR = r_LFSR[29] ^ ~r_LFSR[27];
        end
        30: begin
            r_XNOR = r_LFSR[30] ^ ~r_LFSR[6] ^ ~r_LFSR[4] ^ ~r_LFSR[1];
        end
        31: begin
            r_XNOR = r_LFSR[31] ^ ~r_LFSR[28];
        end
        32: begin
            r_XNOR = r_LFSR[32] ^ ~r_LFSR[22] ^ ~r_LFSR[2] ^ ~r_LFSR[1];
        end
        default: begin
            r_XNOR = 1'b0;
        end
        endcase
    end 
 
    assign o_LFSR_Data = r_LFSR[NUM_BITS:1];
    assign o_LFSR_Done = (r_LFSR[NUM_BITS:1] == i_Seed_Data) ? 1'b1 : 1'b0;
 
endmodule

fpga/Xilinx/Cmod_A7/Max7219-fb/design/random.sv
`timescale 1 ns / 1 ps

// The random number generator based on a Linear Feedback Shift Register (LFSR).

module random

    #(  parameter NUM_BITS = 4  // The number of bits in the random number
    )(
        input   i_Clk,
        input   i_Enable,   // Set on the positive edge of the clock to run RNG
         
        output [NUM_BITS-1:0]   o_Random_Data,  // The current value of the random number
        output                  o_Random_Done
    );
 
    reg r_Seed_DV;
    reg [NUM_BITS-1:0] r_Seed_Data = {1'b1,{(NUM_BITS-1){1'b0}}};

    // The state machine is needed for the one time pulse of the Seed Data Valid (DV) signal
    // to the LFSR module. It's needed to load the seed value into the LFSR at the beginning
    // of operation.

    localparam STATE_IDLE        = 1'b0;
    localparam STATE_SEED_LOADED = 1'b1;
    reg r_State = STATE_IDLE;

    always @(negedge i_Clk) begin
        if (i_Enable == 1'b1) begin
            case (r_State)
                STATE_IDLE: begin
                    r_Seed_DV <= 1'b1;
                    r_State <= STATE_SEED_LOADED;
                end
                STATE_SEED_LOADED: begin
                    r_Seed_DV <= 1'b0;
                    r_State <= STATE_SEED_LOADED;
                end
            endcase
        end
    end

    lfsr
        #(  .NUM_BITS (NUM_BITS)
        ) lfsr_0 (
            .i_Clk      (i_Clk),
            .i_Enable   (i_Enable),
            .i_Seed_DV  (r_Seed_DV),
            .i_Seed_Data(r_Seed_Data),
            .o_LFSR_Data(o_Random_Data),
            .o_LFSR_Done(o_Random_Done)
        );

endmodule

fpga/Xilinx/Cmod_A7/Max7219-fb/design/pattern_random.sv
`timescale 1 ns / 1 ps

// The generator for a random pattern using the random number generator.

module pattern_random

    import max7219_types::*;

    #(  parameter DISP_ROWS     = 1,
        parameter DISP_COLUMNS  = 1,
        parameter CLK_FREQ_HZ   = 1     // 1 Hz
    )(
        input  wire i_Clk,
        input  wire i_Rst,
        output wire [0:7][DISP_ROWS-1:0][DISP_COLUMNS-1:0][15:0] o_MAX7219_DataStream
    );

    // Data registers of the MAX7219 device are complied here for easier access.
    // Note that the function max7219_types::REG_ROW can't be used in the generated code below,
    // so we need to make the assignment here as an alternative solution.

    wire [7:0][3:0] w_REG_ROW = {
        REG_ROW_0, REG_ROW_1, REG_ROW_2, REG_ROW_3, REG_ROW_4, REG_ROW_5, REG_ROW_6, REG_ROW_7
    };

    // The framebuffer

    localparam  FB_WIDTH  = DISP_COLUMNS * 8;
    localparam  FB_HEIGHT = DISP_ROWS    * 8;

    reg fb [0:FB_HEIGHT-1][0:FB_WIDTH-1];

    task clear_fb;
        integer i, j;
        begin
            for (i = 0; i < FB_HEIGHT; i = i + 1) begin
                for (j = 0; j < FB_WIDTH; j = j + 1) begin
                    fb[i][j] <= 1'b0;
                end
            end
        end
    endtask

    task set_row (input integer y, input logic [0:FB_WIDTH-1] data);
        integer x;
        begin
            for (x = 0; x < FB_WIDTH; x = x + 1) begin
                fb[y][x] <= data[x];
            end
        end
    endtask

    // Streams of data to be pushed to the MAX7219 device. There are 8 such streams,
    // one per each row of the 8x8 dot displays.
    // We have to do the mapping it in this way using a generate statement since the streaming
    // concatenation operator {<<{data}} uswed by the macro `MSB is not supported in
    // the non-assignment context.

    generate
        genvar s, r, c;
        for (s = 0; s < 8; s = s + 1) begin : STREAM_GEN
            for (r = 0; r < DISP_ROWS; r = r + 1) begin : ROW_GEN
                for (c = 0; c < DISP_COLUMNS; c = c + 1) begin : COL_GEN
                    assign o_MAX7219_DataStream[7-s][r][c] = {
                        HDR, w_REG_ROW[s], {
                            fb[r*8+7-s][c*8+7], fb[r*8+7-s][c*8+6], fb[r*8+7-s][c*8+5], fb[r*8+7-s][c*8+4],
                            fb[r*8+7-s][c*8+3], fb[r*8+7-s][c*8+2], fb[r*8+7-s][c*8+1], fb[r*8+7-s][c*8+0]
                        }
                    };
                end
            end
        end
    endgenerate

    // The random number generator generates random bits to fill one row of the framebuffer.
    
    reg r_Enable = 1'b0;

    wire [0:FB_WIDTH-1] w_Random_Data;
    wire w_Random_Done;

    random
        #(  .NUM_BITS   (FB_WIDTH)
        ) rand_0 (
            .i_Clk          (i_Clk),
            .i_Enable       (r_Enable),
            .o_Random_Data  (w_Random_Data),
            .o_Random_Done  (w_Random_Done)
        );

    // The state machine runs on the negative edge of the clock

    localparam DELAY_LIMIT = CLK_FREQ_HZ / 4;

    int delay_clocks = 0;
    int y = 0;

    localparam STATE_IDLE = 0, STATE_INITIALIZED = 1, STATE_UPDATE_DISPLAY = 2, STATE_DELAY = 3;
    reg [1:0] r_State;
    reg [1:0] r_State_Next;

    always @(*) begin
        case (r_State)
            STATE_IDLE: begin
                if (i_Rst == 1'b0) begin
                    r_State_Next = STATE_INITIALIZED;
                end else begin
                    r_State_Next = STATE_IDLE;
                end
            end
            STATE_INITIALIZED: begin
                r_State_Next = STATE_UPDATE_DISPLAY;
            end
            STATE_UPDATE_DISPLAY: begin
                if (y < FB_HEIGHT) begin
                    r_State_Next = STATE_UPDATE_DISPLAY;
                end else begin
                    r_State_Next = STATE_DELAY;
                end
            end
            STATE_DELAY: begin
                if (delay_clocks < DELAY_LIMIT) begin
                    r_State_Next = STATE_DELAY;
                end else begin
                    r_State_Next = STATE_UPDATE_DISPLAY;
                end
            end
            default: begin
                r_State_Next = STATE_IDLE;
            end
        endcase
    end
    always @(negedge i_Clk or posedge i_Rst) begin
        if (i_Rst) begin
            r_State <= STATE_IDLE;
        end else begin
            r_State <= r_State_Next;
        end
    end
    always @(negedge i_Clk or posedge i_Rst) begin
        if (i_Rst) begin
            delay_clocks <= 0;
            y <= 0;
            r_Enable <= 1'b0;
        end else begin
            case (r_State)
                STATE_IDLE: begin
                    delay_clocks <= 0;
                    y <= 0;
                    r_Enable <= 1'b0;
                end
                STATE_INITIALIZED: begin
                    r_Enable <= 1'b1;
                    clear_fb();
                end
                STATE_UPDATE_DISPLAY: begin
                    if (y < FB_HEIGHT) begin
                        y <= y + 1;
                        set_row(y, w_Random_Data);
                    end else begin
                        y <= 0;
                        //r_Enable <= 1'b0;
                    end
                end
                STATE_DELAY: begin
                    if (delay_clocks < DELAY_LIMIT) begin
                        delay_clocks <= delay_clocks + 1;
                    end else begin
                        delay_clocks <= 0;
                        //r_Enable <= 1'b1;
                    end
                end
                default: begin
                    r_State_Next = STATE_IDLE;
                end
            endcase
        end
    end

endmodule

fpga/Xilinx/Cmod_A7/Max7219-fb/tb/pattern_random_tb.sv
`timescale 1 ns / 1 ps

module pattern_random_tb ();
 
    localparam DISP_ROWS     = 1;
    localparam DISP_COLUMNS  = 1;
    localparam CLK_FREQ_HZ   = 8;  // 8 Hz
    reg r_Clk;
    reg r_Rst;
    wire [0:7][DISP_ROWS-1:0][DISP_COLUMNS-1:0][15:0] w_MAX7219_DataStream;

    
    pattern_random
        #(  .DISP_ROWS(DISP_ROWS),
            .DISP_COLUMNS(DISP_COLUMNS),
            .CLK_FREQ_HZ(CLK_FREQ_HZ)
        ) pattern_random_0 (
            .i_Clk(r_Clk),
            .i_Rst(r_Rst),
            .o_MAX7219_DataStream(w_MAX7219_DataStream)
        ); 
  
    initial begin
        $dumpfile("pattern_random.vcd");
        $dumpvars(0);
        r_Clk = 1'b0;
        r_Rst = 1'b0;
        #1000 $finish;
    end

    always @(*) begin
        #1 r_Clk <= ~r_Clk;
    end
   
endmodule

fpga/Xilinx/Cmod_A7/Max7219-fb/build/PC101137/run/pattern_random.vcd
$date
	Mon Jan 12 22:06:25 2026
$end
$version
	Icarus Verilog
$end
$timescale
	1ps
$end
$scope module pattern_random_tb $end
$var wire 128 ! w_MAX7219_DataStream [127:0] $end
$var parameter 32 " CLK_FREQ_HZ $end
$var parameter 32 # DISP_COLUMNS $end
$var parameter 32 $ DISP_ROWS $end
$var reg 1 % r_Clk $end
$var reg 1 & r_Rst $end
$scope module pattern_random_0 $end
$var wire 1 % i_Clk $end
$var wire 1 & i_Rst $end
$var wire 32 ' w_REG_ROW [31:0] $end
$var wire 1 ( w_Random_Done $end
$var wire 8 ) w_Random_Data [0:7] $end
$var wire 128 * o_MAX7219_DataStream [127:0] $end
$var parameter 32 + CLK_FREQ_HZ $end
$var parameter 32 , DELAY_LIMIT $end
$var parameter 32 - DISP_COLUMNS $end
$var parameter 32 . DISP_ROWS $end
$var parameter 64 / FB_HEIGHT $end
$var parameter 64 0 FB_WIDTH $end
$var parameter 32 1 STATE_DELAY $end
$var parameter 32 2 STATE_IDLE $end
$var parameter 32 3 STATE_INITIALIZED $end
$var parameter 32 4 STATE_UPDATE_DISPLAY $end
$var reg 1 5 r_Enable $end
$var reg 2 6 r_State [1:0] $end
$var reg 2 7 r_State_Next [1:0] $end
$var integer 32 8 delay_clocks [31:0] $end
$var integer 32 9 y [31:0] $end
$scope begin STREAM_GEN[0] $end
$var parameter 2 : s $end
$scope begin ROW_GEN[0] $end
$var parameter 2 ; r $end
$scope begin COL_GEN[0] $end
$var parameter 2 < c $end
$upscope $end
$upscope $end
$upscope $end
$scope begin STREAM_GEN[1] $end
$var parameter 2 = s $end
$scope begin ROW_GEN[0] $end
$var parameter 2 > r $end
$scope begin COL_GEN[0] $end
$var parameter 2 ? c $end
$upscope $end
$upscope $end
$upscope $end
$scope begin STREAM_GEN[2] $end
$var parameter 3 @ s $end
$scope begin ROW_GEN[0] $end
$var parameter 2 A r $end
$scope begin COL_GEN[0] $end
$var parameter 2 B c $end
$upscope $end
$upscope $end
$upscope $end
$scope begin STREAM_GEN[3] $end
$var parameter 3 C s $end
$scope begin ROW_GEN[0] $end
$var parameter 2 D r $end
$scope begin COL_GEN[0] $end
$var parameter 2 E c $end
$upscope $end
$upscope $end
$upscope $end
$scope begin STREAM_GEN[4] $end
$var parameter 4 F s $end
$scope begin ROW_GEN[0] $end
$var parameter 2 G r $end
$scope begin COL_GEN[0] $end
$var parameter 2 H c $end
$upscope $end
$upscope $end
$upscope $end
$scope begin STREAM_GEN[5] $end
$var parameter 4 I s $end
$scope begin ROW_GEN[0] $end
$var parameter 2 J r $end
$scope begin COL_GEN[0] $end
$var parameter 2 K c $end
$upscope $end
$upscope $end
$upscope $end
$scope begin STREAM_GEN[6] $end
$var parameter 4 L s $end
$scope begin ROW_GEN[0] $end
$var parameter 2 M r $end
$scope begin COL_GEN[0] $end
$var parameter 2 N c $end
$upscope $end
$upscope $end
$upscope $end
$scope begin STREAM_GEN[7] $end
$var parameter 4 O s $end
$scope begin ROW_GEN[0] $end
$var parameter 2 P r $end
$scope begin COL_GEN[0] $end
$var parameter 2 Q c $end
$upscope $end
$upscope $end
$upscope $end
$scope module rand_0 $end
$var wire 1 % i_Clk $end
$var wire 1 5 i_Enable $end
$var wire 1 ( o_Random_Done $end
$var wire 8 R o_Random_Data [7:0] $end
$var parameter 64 S NUM_BITS $end
$var parameter 1 T STATE_IDLE $end
$var parameter 1 U STATE_SEED_LOADED $end
$var reg 1 V r_Seed_DV $end
$var reg 8 W r_Seed_Data [7:0] $end
$var reg 1 X r_State $end
$scope module lfsr_0 $end
$var wire 1 % i_Clk $end
$var wire 1 5 i_Enable $end
$var wire 1 V i_Seed_DV $end
$var wire 8 Y i_Seed_Data [7:0] $end
$var wire 8 Z o_LFSR_Data [7:0] $end
$var wire 1 ( o_LFSR_Done $end
$var parameter 64 [ NUM_BITS $end
$var reg 8 \ r_LFSR [8:1] $end
$var reg 1 ] r_XNOR $end
$upscope $end
$upscope $end
$scope task clear_fb $end
$var integer 32 ^ i [31:0] $end
$var integer 32 _ j [31:0] $end
$upscope $end
$scope task set_row $end
$var reg 8 ` data [0:7] $end
$var integer 32 a x [31:0] $end
$var integer 32 b y [31:0] $end
$upscope $end
$upscope $end
$upscope $end
$enddefinitions $end
$comment Show the parameter values. $end
$dumpall
b1000 [
1U
0T
b1000 S
b0 Q
b0 P
b111 O
b0 N
b0 M
b110 L
b0 K
b0 J
b101 I
b0 H
b0 G
b100 F
b0 E
b0 D
b11 C
b0 B
b0 A
b10 @
b0 ?
b0 >
b1 =
b0 <
b0 ;
b0 :
b10 4
b1 3
b0 2
b11 1
b1000 0
b1000 /
b1 .
b1 -
b10 ,
b1000 +
b1 $
b1 #
b1000 "
$end
#0
$dumpvars
bx b
bx a
bx `
bx _
bx ^
0]
b0 \
b0 Z
b10000000 Y
0X
b10000000 W
xV
b0 R
b0 9
b0 8
b1 7
b0 6
05
b1xxxxxxxx00000010xxxxxxxx00000011xxxxxxxx00000100xxxxxxxx00000101xxxxxxxx00000110xxxxxxxx00000111xxxxxxxx00001000xxxxxxxx *
b0 )
0(
b10010001101000101011001111000 '
0&
0%
b1xxxxxxxx00000010xxxxxxxx00000011xxxxxxxx00000100xxxxxxxx00000101xxxxxxxx00000110xxxxxxxx00000111xxxxxxxx00001000xxxxxxxx !
$end
#1000
1%
#2000
b10 7
b1 6
0%
#3000
1%
#4000
b1000000000000001000000000000000110000000000000100000000000000010100000000000001100000000000000111000000000000100000000000 !
b1000000000000001000000000000000110000000000000100000000000000010100000000000001100000000000000111000000000000100000000000 *
b10 6
15
b1000 _
b1000 ^
0%
#5000
1%
#6000
1X
1V
b1 9
b1000 a
b0 `
b0 b
0%
#7000
1(
b10000000 )
b10000000 R
b10000000 Z
b10000000 \
1%
#8000
0V
b1000000000000001000000001000000110000000000000100000000000000010100000000000001100000000000000111000000000000100000000000 !
b1000000000000001000000001000000110000000000000100000000000000010100000000000001100000000000000111000000000000100000000000 *
b10 9
b1000 a
b10000000 `
b1 b
0%
#9000
1]
0(
b0 )
b0 R
b0 Z
b0 \
1%
#10000
b11 9
b1000 a
b0 `
b10 b
0%
#11000
b1 )
b1 R
b1 Z
b1 \
1%
#12000
b1000000000000001000000001000000110000000000000100100000000000010100000000000001100000000000000111000000000000100000000000 !
b1000000000000001000000001000000110000000000000100100000000000010100000000000001100000000000000111000000000000100000000000 *
b100 9
b1000 a
b1 `
b11 b
0%
#13000
b11 )
b11 R
b11 Z
b11 \
1%
#14000
b1000000000000001000000001000000110000000000000100100000000000010111000000000001100000000000000111000000000000100000000000 !
b1000000000000001000000001000000110000000000000100100000000000010111000000000001100000000000000111000000000000100000000000 *
b101 9
b1000 a
b11 `
b100 b
0%
#15000
b111 )
b111 R
b111 Z
b111 \
1%
#16000
b1000000000000001000000001000000110000000000000100100000000000010111000000000001101110000000000111000000000000100000000000 !
b1000000000000001000000001000000110000000000000100100000000000010111000000000001101110000000000111000000000000100000000000 *
b110 9
b1000 a
b111 `
b101 b
0%
#17000
0]
b1111 )
b1111 R
b1111 Z
b1111 \
1%
#18000
b1000000000000001000000001000000110000000000000100100000000000010111000000000001101110000000000111111100000000100000000000 !
b1000000000000001000000001000000110000000000000100100000000000010111000000000001101110000000000111111100000000100000000000 *
b111 9
b1000 a
b1111 `
b110 b
0%
#19000
1]
b11110 )
b11110 R
b11110 Z
b11110 \
1%
#20000
b11 7
b1000000000000001000000001000000110000000000000100100000000000010111000000000001101110000000000111111100000000100001111000 !
b1000000000000001000000001000000110000000000000100100000000000010111000000000001101110000000000111111100000000100001111000 *
b1000 9
b1000 a
b11110 `
b111 b
0%
#21000
0]
b111101 )
b111101 R
b111101 Z
b111101 \
1%
#22000
b11 6
b0 9
0%
#23000
b1111010 )
b1111010 R
b1111010 Z
b1111010 \
1%
#24000
b1 8
0%
#25000
b11110100 )
b11110100 R
b11110100 Z
b11110100 \
1%
#26000
b10 7
b10 8
0%
#27000
b11101000 )
b11101000 R
b11101000 Z
b11101000 \
1%
#28000
b0 8
b10 6
0%
#29000
1]
b11010000 )
b11010000 R
b11010000 Z
b11010000 \
1%
#30000
b1000010110000001000000001000000110000000000000100100000000000010111000000000001101110000000000111111100000000100001111000 !
b1000010110000001000000001000000110000000000000100100000000000010111000000000001101110000000000111111100000000100001111000 *
b1 9
b1000 a
b11010000 `
b0 b
0%
#31000
b10100001 )
b10100001 R
b10100001 Z
b10100001 \
1%
#32000
b1000010110000001010000101000000110000000000000100100000000000010111000000000001101110000000000111111100000000100001111000 !
b1000010110000001010000101000000110000000000000100100000000000010111000000000001101110000000000111111100000000100001111000 *
b10 9
b1000 a
b10100001 `
b1 b
0%
#33000
b1000011 )
b1000011 R
b1000011 Z
b1000011 \
1%
#34000
b1000010110000001010000101000000111100001000000100100000000000010111000000000001101110000000000111111100000000100001111000 !
b1000010110000001010000101000000111100001000000100100000000000010111000000000001101110000000000111111100000000100001111000 *
b11 9
b1000 a
b1000011 `
b10 b
0%
#35000
0]
b10000111 )
b10000111 R
b10000111 Z
b10000111 \
1%
#36000
b1000010110000001010000101000000111100001000000100111000010000010111000000000001101110000000000111111100000000100001111000 !
b1000010110000001010000101000000111100001000000100111000010000010111000000000001101110000000000111111100000000100001111000 *
b100 9
b1000 a
b10000111 `
b11 b
0%
#37000
b1110 )
b1110 R
b1110 Z
b1110 \
1%
#38000
b1000010110000001010000101000000111100001000000100111000010000010101110000000001101110000000000111111100000000100001111000 !
b1000010110000001010000101000000111100001000000100111000010000010101110000000001101110000000000111111100000000100001111000 *
b101 9
b1000 a
b1110 `
b100 b
0%
#39000
1]
b11100 )
b11100 R
b11100 Z
b11100 \
1%
#40000
b1000010110000001010000101000000111100001000000100111000010000010101110000000001100011100000000111111100000000100001111000 !
b1000010110000001010000101000000111100001000000100111000010000010101110000000001100011100000000111111100000000100001111000 *
b110 9
b1000 a
b11100 `
b101 b
0%
#41000
0]
b111001 )
b111001 R
b111001 Z
b111001 \
1%
#42000
b1000010110000001010000101000000111100001000000100111000010000010101110000000001100011100000000111100111000000100001111000 !
b1000010110000001010000101000000111100001000000100111000010000010101110000000001100011100000000111100111000000100001111000 *
b111 9
b1000 a
b111001 `
b110 b
0%
#43000
1]
b1110010 )
b1110010 R
b1110010 Z
b1110010 \
1%
#44000
b11 7
b1000010110000001010000101000000111100001000000100111000010000010101110000000001100011100000000111100111000000100001001110 !
b1000010110000001010000101000000111100001000000100111000010000010101110000000001100011100000000111100111000000100001001110 *
b1000 9
b1000 a
b1110010 `
b111 b
0%
#45000
b11100101 )
b11100101 R
b11100101 Z
b11100101 \
1%
#46000
b11 6
b0 9
0%
#47000
b11001011 )
b11001011 R
b11001011 Z
b11001011 \
1%
#48000
b1 8
0%
#49000
b10010111 )
b10010111 R
b10010111 Z
b10010111 \
1%
#50000
b10 7
b10 8
0%
#51000
b101111 )
b101111 R
b101111 Z
b101111 \
1%
#52000
b0 8
b10 6
0%
#53000
b1011111 )
b1011111 R
b1011111 Z
b1011111 \
1%
#54000
b1111110100000001010000101000000111100001000000100111000010000010101110000000001100011100000000111100111000000100001001110 !
b1111110100000001010000101000000111100001000000100111000010000010101110000000001100011100000000111100111000000100001001110 *
b1 9
b1000 a
b1011111 `
b0 b
0%
#55000
b10111111 )
b10111111 R
b10111111 Z
b10111111 \
1%
#56000
b1111110100000001011111101000000111100001000000100111000010000010101110000000001100011100000000111100111000000100001001110 !
b1111110100000001011111101000000111100001000000100111000010000010101110000000001100011100000000111100111000000100001001110 *
b10 9
b1000 a
b10111111 `
b1 b
0%
#57000
0]
b1111111 )
b1111111 R
b1111111 Z
b1111111 \
1%
#58000
b1111110100000001011111101000000111111111000000100111000010000010101110000000001100011100000000111100111000000100001001110 !
b1111110100000001011111101000000111111111000000100111000010000010101110000000001100011100000000111100111000000100001001110 *
b11 9
b1000 a
b1111111 `
b10 b
0%
#59000
1]
b11111110 )
b11111110 R
b11111110 Z
b11111110 \
1%
#60000
b1111110100000001011111101000000111111111000000100011111110000010101110000000001100011100000000111100111000000100001001110 !
b1111110100000001011111101000000111111111000000100011111110000010101110000000001100011100000000111100111000000100001001110 *
b100 9
b1000 a
b11111110 `
b11 b
0%
#61000
b11111101 )
b11111101 R
b11111101 Z
b11111101 \
1%
#62000
b1111110100000001011111101000000111111111000000100011111110000010110111111000001100011100000000111100111000000100001001110 !
b1111110100000001011111101000000111111111000000100011111110000010110111111000001100011100000000111100111000000100001001110 *
b101 9
b1000 a
b11111101 `
b100 b
0%
#63000
b11111011 )
b11111011 R
b11111011 Z
b11111011 \
1%
#64000
b1111110100000001011111101000000111111111000000100011111110000010110111111000001101101111100000111100111000000100001001110 !
b1111110100000001011111101000000111111111000000100011111110000010110111111000001101101111100000111100111000000100001001110 *
b110 9
b1000 a
b11111011 `
b101 b
0%
#65000
0]
b11110111 )
b11110111 R
b11110111 Z
b11110111 \
1%
#66000
b1111110100000001011111101000000111111111000000100011111110000010110111111000001101101111100000111111011110000100001001110 !
b1111110100000001011111101000000111111111000000100011111110000010110111111000001101101111100000111111011110000100001001110 *
b111 9
b1000 a
b11110111 `
b110 b
0%
#67000
b11101110 )
b11101110 R
b11101110 Z
b11101110 \
1%
#68000
b11 7
b1111110100000001011111101000000111111111000000100011111110000010110111111000001101101111100000111111011110000100001110111 !
b1111110100000001011111101000000111111111000000100011111110000010110111111000001101101111100000111111011110000100001110111 *
b1000 9
b1000 a
b11101110 `
b111 b
0%
#69000
b11011100 )
b11011100 R
b11011100 Z
b11011100 \
1%
#70000
b11 6
b0 9
0%
#71000
1]
b10111000 )
b10111000 R
b10111000 Z
b10111000 \
1%
#72000
b1 8
0%
#73000
b1110001 )
b1110001 R
b1110001 Z
b1110001 \
1%
#74000
b10 7
b10 8
0%
#75000
b11100011 )
b11100011 R
b11100011 Z
b11100011 \
1%
#76000
b0 8
b10 6
0%
#77000
0]
b11000111 )
b11000111 R
b11000111 Z
b11000111 \
1%
#78000
b1111000110000001011111101000000111111111000000100011111110000010110111111000001101101111100000111111011110000100001110111 !
b1111000110000001011111101000000111111111000000100011111110000010110111111000001101101111100000111111011110000100001110111 *
b1 9
b1000 a
b11000111 `
b0 b
0%
#79000
1]
b10001110 )
b10001110 R
b10001110 Z
b10001110 \
1%
#80000
b1111000110000001001110001000000111111111000000100011111110000010110111111000001101101111100000111111011110000100001110111 !
b1111000110000001001110001000000111111111000000100011111110000010110111111000001101101111100000111111011110000100001110111 *
b10 9
b1000 a
b10001110 `
b1 b
0%
#81000
b11101 )
b11101 R
b11101 Z
b11101 \
1%
#82000
b1111000110000001001110001000000111011100000000100011111110000010110111111000001101101111100000111111011110000100001110111 !
b1111000110000001001110001000000111011100000000100011111110000010110111111000001101101111100000111111011110000100001110111 *
b11 9
b1000 a
b11101 `
b10 b
0%
#83000
0]
b111011 )
b111011 R
b111011 Z
b111011 \
1%
#84000
b1111000110000001001110001000000111011100000000100110111000000010110111111000001101101111100000111111011110000100001110111 !
b1111000110000001001110001000000111011100000000100110111000000010110111111000001101101111100000111111011110000100001110111 *
b100 9
b1000 a
b111011 `
b11 b
0%
#85000
1]
b1110110 )
b1110110 R
b1110110 Z
b1110110 \
1%
#86000
b1111000110000001001110001000000111011100000000100110111000000010101101110000001101101111100000111111011110000100001110111 !
b1111000110000001001110001000000111011100000000100110111000000010101101110000001101101111100000111111011110000100001110111 *
b101 9
b1000 a
b1110110 `
b100 b
0%
#87000
0]
b11101101 )
b11101101 R
b11101101 Z
b11101101 \
1%
#88000
b1111000110000001001110001000000111011100000000100110111000000010101101110000001101011011100000111111011110000100001110111 !
b1111000110000001001110001000000111011100000000100110111000000010101101110000001101011011100000111111011110000100001110111 *
b110 9
b1000 a
b11101101 `
b101 b
0%
#89000
b11011010 )
b11011010 R
b11011010 Z
b11011010 \
1%
#90000
b1111000110000001001110001000000111011100000000100110111000000010101101110000001101011011100000111010110110000100001110111 !
b1111000110000001001110001000000111011100000000100110111000000010101101110000001101011011100000111010110110000100001110111 *
b111 9
b1000 a
b11011010 `
b110 b
0%
#91000
b10110100 )
b10110100 R
b10110100 Z
b10110100 \
1%
#92000
b11 7
b1111000110000001001110001000000111011100000000100110111000000010101101110000001101011011100000111010110110000100000101101 !
b1111000110000001001110001000000111011100000000100110111000000010101101110000001101011011100000111010110110000100000101101 *
b1000 9
b1000 a
b10110100 `
b111 b
0%
#93000
1]
b1101000 )
b1101000 R
b1101000 Z
b1101000 \
1%
#94000
b11 6
b0 9
0%
#95000
b11010001 )
b11010001 R
b11010001 Z
b11010001 \
1%
#96000
b1 8
0%
#97000
b10100011 )
b10100011 R
b10100011 Z
b10100011 \
1%
#98000
b10 7
b10 8
0%
#99000
b1000111 )
b1000111 R
b1000111 Z
b1000111 \
1%
#100000
b0 8
b10 6
0%
#101000
b10001111 )
b10001111 R
b10001111 Z
b10001111 \
1%
#102000
b1111100010000001001110001000000111011100000000100110111000000010101101110000001101011011100000111010110110000100000101101 !
b1111100010000001001110001000000111011100000000100110111000000010101101110000001101011011100000111010110110000100000101101 *
b1 9
b1000 a
b10001111 `
b0 b
0%
#103000
b11111 )
b11111 R
b11111 Z
b11111 \
1%
#104000
b1111100010000001011111000000000111011100000000100110111000000010101101110000001101011011100000111010110110000100000101101 !
b1111100010000001011111000000000111011100000000100110111000000010101101110000001101011011100000111010110110000100000101101 *
b10 9
b1000 a
b11111 `
b1 b
0%
