fpga/Xilinx/Cmod_A7/Max7219-fb/design/lfsr.sv
`timescale 1 ns / 1 ps

// The implementation is based on an idea outlined in http://www.nandland.com
//
// A LFSR or Linear Feedback Shift Register is meant for generating pseudo-random
// data in FPGA. This module creates an LFSR whose width gets set by a parameter.
// The o_LFSR_Done will pulse for a duration of 1 clock period once all combinations
// of the LFSR are complete.  The number of clock
// cycles that it takes o_LFSR_Done to pulse is equal to 2^NUM_BITS-1. For
// example setting NUM_BITS to 5 means that o_LFSR_Done will pulse every
// 2^5-1 = 31 clock cycles. o_LFSR_Data will change on each clock cycle that
// the module is enabled.

module lfsr

    #(  parameter NUM_BITS = 4  // The number of bits in the LFSR
    )(
        input   i_Clk,
        input   i_Enable,   // Set on the positive edge of the clock to run LFSR
 
        // Optional Seed Value
        input                   i_Seed_DV,      // Set on the positive edge of the clock to load seed data
        input [NUM_BITS-1:0]    i_Seed_Data,    // Data to initialize the LFSR with
        
        output [NUM_BITS-1:0]   o_LFSR_Data,    // The current value of the LFSR (the initial value is 0)
        output                  o_LFSR_Done
    );
 
    reg [NUM_BITS:1] r_LFSR = '0;
    reg              r_XNOR = 1'b0;
 
 
    // Purpose: Load up LFSR with Seed if Data Valid (DV) pulse is detected.
    // Othewise just run LFSR when enabled.

    always @(posedge i_Clk) begin
        if (i_Enable == 1'b1) begin
            if (i_Seed_DV == 1'b1) begin
                r_LFSR <= i_Seed_Data;
            end else begin
                r_LFSR <= {r_LFSR[NUM_BITS-1:1], r_XNOR};
            end
        end
    end
 
    // Create Feedback Polynomials.  Based on Application Note:
    // http://www.xilinx.com/support/documentation/application_notes/xapp052.pdf

    always @(*) begin
        case (NUM_BITS)
        3: begin
            r_XNOR = r_LFSR[3] ^ ~r_LFSR[2];
        end
        4: begin
            r_XNOR = r_LFSR[4] ^ ~r_LFSR[3];
        end
        5: begin
            r_XNOR = r_LFSR[5] ^ ~r_LFSR[3];
        end
        6: begin
            r_XNOR = r_LFSR[6] ^ ~r_LFSR[5];
        end
        7: begin
            r_XNOR = r_LFSR[7] ^ ~r_LFSR[6];
        end
        8: begin
            r_XNOR = r_LFSR[8] ^ ~r_LFSR[6] ^ ~r_LFSR[5] ^ ~r_LFSR[4];
        end
        9: begin
            r_XNOR = r_LFSR[9] ^ ~r_LFSR[5];
        end
        10: begin
            r_XNOR = r_LFSR[10] ^ ~r_LFSR[7];
        end
        11: begin
            r_XNOR = r_LFSR[11] ^ ~r_LFSR[9];
        end
        12: begin
            r_XNOR = r_LFSR[12] ^ ~r_LFSR[6] ^ ~r_LFSR[4] ^ ~r_LFSR[1];
        end
        13: begin
            r_XNOR = r_LFSR[13] ^ ~r_LFSR[4] ^ ~r_LFSR[3] ^ ~r_LFSR[1];
        end
        14: begin
            r_XNOR = r_LFSR[14] ^ ~r_LFSR[5] ^ ~r_LFSR[3] ^ ~r_LFSR[1];
        end
        15: begin
            r_XNOR = r_LFSR[15] ^ ~r_LFSR[14];
        end
        16: begin
            r_XNOR = r_LFSR[16] ^ ~r_LFSR[15] ^ ~r_LFSR[13] ^ ~r_LFSR[4];
            end
        17: begin
            r_XNOR = r_LFSR[17] ^ ~r_LFSR[14];
        end
        18: begin
            r_XNOR = r_LFSR[18] ^ ~r_LFSR[11];
        end
        19: begin
            r_XNOR = r_LFSR[19] ^ ~r_LFSR[6] ^ ~r_LFSR[2] ^ ~r_LFSR[1];
        end
        20: begin
            r_XNOR = r_LFSR[20] ^ ~r_LFSR[17];
        end
        21: begin
            r_XNOR = r_LFSR[21] ^ ~r_LFSR[19];
        end
        22: begin
            r_XNOR = r_LFSR[22] ^ ~r_LFSR[21];
        end
        23: begin
            r_XNOR = r_LFSR[23] ^ ~r_LFSR[18];
        end
        24: begin
            r_XNOR = r_LFSR[24] ^ ~r_LFSR[23] ^ ~r_LFSR[22] ^ ~r_LFSR[17];
        end
        25: begin
            r_XNOR = r_LFSR[25] ^ ~r_LFSR[22];
        end
        26: begin
            r_XNOR = r_LFSR[26] ^ ~r_LFSR[6] ^ ~r_LFSR[2] ^ ~r_LFSR[1];
        end
        27: begin
            r_XNOR = r_LFSR[27] ^ ~r_LFSR[5] ^ ~r_LFSR[2] ^ ~r_LFSR[1];
        end
        28: begin
            r_XNOR = r_LFSR[28] ^ ~r_LFSR[25];
        end
        29: begin
            r_XNOR = r_LFSR[29] ^ ~r_LFSR[27];
        end
        30: begin
            r_XNOR = r_LFSR[30] ^ ~r_LFSR[6] ^ ~r_LFSR[4] ^ ~r_LFSR[1];
        end
        31: begin
            r_XNOR = r_LFSR[31] ^ ~r_LFSR[28];
        end
        32: begin
            r_XNOR = r_LFSR[32] ^ ~r_LFSR[22] ^ ~r_LFSR[2] ^ ~r_LFSR[1];
        end
        default: begin
            r_XNOR = 1'b0;
        end
        endcase
    end 
 
    assign o_LFSR_Data = r_LFSR[NUM_BITS:1];
    assign o_LFSR_Done = (r_LFSR[NUM_BITS:1] == i_Seed_Data) ? 1'b1 : 1'b0;
 
endmodule

fpga/Xilinx/Cmod_A7/Max7219-fb/design/random.sv
`timescale 1 ns / 1 ps

// The random number generator based on a Linear Feedback Shift Register (LFSR).

module random

    #(  parameter NUM_BITS = 4  // The number of bits in the random number
    )(
        input   i_Clk,
        input   i_Enable,   // Set on the positive edge of the clock to run RNG
         
        output [NUM_BITS-1:0]   o_Random_Data,  // The current value of the random number
        output                  o_Random_Done
    );
 
    reg r_Seed_DV;
    reg [NUM_BITS-1:0] r_Seed_Data = {1'b1,{(NUM_BITS-1){1'b0}}};

    // The state machine is needed for the one time pulse of the Seed Data Valid (DV) signal
    // to the LFSR module. It's needed to load the seed value into the LFSR at the beginning
    // of operation.

    localparam STATE_IDLE        = 1'b0;
    localparam STATE_SEED_LOADED = 1'b1;
    reg r_State = STATE_IDLE;

    always @(negedge i_Clk) begin
        if (i_Enable == 1'b1) begin
            case (r_State)
                STATE_IDLE: begin
                    r_Seed_DV <= 1'b1;
                    r_State <= STATE_SEED_LOADED;
                end
                STATE_SEED_LOADED: begin
                    r_Seed_DV <= 1'b0;
                    r_State <= STATE_SEED_LOADED;
                end
            endcase
        end
    end

    lfsr
        #(  .NUM_BITS (NUM_BITS)
        ) lfsr_0 (
            .i_Clk      (i_Clk),
            .i_Enable   (i_Enable),
            .i_Seed_DV  (r_Seed_DV),
            .i_Seed_Data(r_Seed_Data),
            .o_LFSR_Data(o_Random_Data),
            .o_LFSR_Done(o_Random_Done)
        );

endmodule

fpga/Xilinx/Cmod_A7/Max7219-fb/tb/random_tb.sv
`timescale 1 ns / 1 ps

module random_tb ();
 
    localparam NUM_BITS = 4;
    
    reg r_Clk;
    reg r_Enable;

    wire [NUM_BITS-1:0] w_Random_Data;
    wire w_Random_Done;
    
    random
        #(  .NUM_BITS   (NUM_BITS)
        ) rand_0 (
            .i_Clk          (r_Clk),
            .i_Enable       (r_Enable),
            .o_Random_Data  (w_Random_Data),
            .o_Random_Done  (w_Random_Done)
        );
  
    initial begin
        $dumpfile("random.vcd");
        $dumpvars(0);
        r_Clk = 1'b0;
        @(negedge r_Clk); r_Enable = 1'b1;
        @(negedge r_Clk); r_Enable = 1'b0;
        #5;
        @(negedge r_Clk); r_Enable = 1'b1;
        #64 $finish;
    end

    always @(*) begin
        #1 r_Clk <= ~r_Clk;
    end
   
endmodule

fpga/Xilinx/Cmod_A7/Max7219-fb/build/PC101137/run/random.vcd
$date
	Mon Jan 12 22:06:25 2026
$end
$version
	Icarus Verilog
$end
$timescale
	1ps
$end
$scope module random_tb $end
$var wire 1 ! w_Random_Done $end
$var wire 4 " w_Random_Data [3:0] $end
$var parameter 32 # NUM_BITS $end
$var reg 1 $ r_Clk $end
$var reg 1 % r_Enable $end
$scope module rand_0 $end
$var wire 1 $ i_Clk $end
$var wire 1 % i_Enable $end
$var wire 1 ! o_Random_Done $end
$var wire 4 & o_Random_Data [3:0] $end
$var parameter 32 ' NUM_BITS $end
$var parameter 1 ( STATE_IDLE $end
$var parameter 1 ) STATE_SEED_LOADED $end
$var reg 1 * r_Seed_DV $end
$var reg 4 + r_Seed_Data [3:0] $end
$var reg 1 , r_State $end
$scope module lfsr_0 $end
$var wire 1 $ i_Clk $end
$var wire 1 % i_Enable $end
$var wire 1 * i_Seed_DV $end
$var wire 4 - i_Seed_Data [3:0] $end
$var wire 4 . o_LFSR_Data [3:0] $end
$var wire 1 ! o_LFSR_Done $end
$var parameter 32 / NUM_BITS $end
$var reg 4 0 r_LFSR [4:1] $end
$var reg 1 1 r_XNOR $end
$upscope $end
$upscope $end
$upscope $end
$enddefinitions $end
$comment Show the parameter values. $end
$dumpall
b100 /
1)
0(
b100 '
b100 #
$end
#0
$dumpvars
01
b0 0
b0 .
b1000 -
0,
b1000 +
x*
b0 &
x%
0$
b0 "
0!
$end
#1000
1$
#2000
1%
0$
#3000
1$
#4000
0%
0$
#5000
1$
#6000
0$
#7000
1$
#8000
0$
#9000
1$
#10000
1,
1*
1%
0$
#11000
1!
b1000 "
b1000 &
b1000 .
b1000 0
1$
#12000
0*
0$
#13000
11
0!
b0 "
b0 &
b0 .
b0 0
1$
#14000
0$
#15000
b1 "
b1 &
b1 .
b1 0
1$
#16000
0$
#17000
b11 "
b11 &
b11 .
b11 0
1$
#18000
0$
#19000
01
b111 "
b111 &
b111 .
b111 0
1$
#20000
0$
#21000
11
b1110 "
b1110 &
b1110 .
b1110 0
1$
#22000
0$
#23000
b1101 "
b1101 &
b1101 .
b1101 0
1$
#24000
0$
#25000
01
b1011 "
b1011 &
b1011 .
b1011 0
1$
#26000
0$
#27000
b110 "
b110 &
b110 .
b110 0
1$
#28000
0$
#29000
11
b1100 "
b1100 &
b1100 .
b1100 0
1$
#30000
0$
#31000
01
b1001 "
b1001 &
b1001 .
b1001 0
1$
#32000
0$
#33000
11
b10 "
b10 &
b10 .
b10 0
1$
#34000
0$
#35000
01
b101 "
b101 &
b101 .
b101 0
1$
#36000
0$
#37000
b1010 "
b1010 &
b1010 .
b1010 0
1$
#38000
0$
#39000
b100 "
b100 &
b100 .
b100 0
1$
#40000
0$
#41000
1!
b1000 "
b1000 &
b1000 .
b1000 0
1$
#42000
0$
#43000
11
0!
b0 "
b0 &
b0 .
b0 0
1$
#44000
0$
#45000
b1 "
b1 &
b1 .
b1 0
1$
#46000
0$
#47000
b11 "
b11 &
b11 .
b11 0
1$
#48000
0$
#49000
01
b111 "
b111 &
b111 .
b111 0
1$
#50000
0$
#51000
11
b1110 "
b1110 &
b1110 .
b1110 0
1$
#52000
0$
#53000
b1101 "
b1101 &
b1101 .
b1101 0
1$
#54000
0$
#55000
01
b1011 "
b1011 &
b1011 .
b1011 0
1$
#56000
0$
#57000
b110 "
b110 &
b110 .
b110 0
1$
#58000
0$
#59000
11
b1100 "
b1100 &
b1100 .
b1100 0
1$
#60000
0$
#61000
01
b1001 "
b1001 &
b1001 .
b1001 0
1$
#62000
0$
#63000
11
b10 "
b10 &
b10 .
b10 0
1$
#64000
0$
#65000
01
b101 "
b101 &
b101 .
b101 0
1$
#66000
0$
#67000
b1010 "
b1010 &
b1010 .
b1010 0
1$
#68000
0$
#69000
b100 "
b100 &
b100 .
b100 0
1$
#70000
0$
#71000
1!
b1000 "
b1000 &
b1000 .
b1000 0
1$
#72000
0$
#73000
11
0!
b0 "
b0 &
b0 .
b0 0
1$
